.gitignore
MANIFEST.in
README.rst
bootstrap.py
buildout.cfg
plonetheme.responsive1140-configure.zcml
setup.py
docs/HISTORY.txt
docs/INSTALL.txt
docs/LICENSE.GPL
docs/LICENSE.txt
plonetheme/__init__.py
plonetheme.responsive1140.egg-info/PKG-INFO
plonetheme.responsive1140.egg-info/SOURCES.txt
plonetheme.responsive1140.egg-info/dependency_links.txt
plonetheme.responsive1140.egg-info/entry_points.txt
plonetheme.responsive1140.egg-info/namespace_packages.txt
plonetheme.responsive1140.egg-info/not-zip-safe
plonetheme.responsive1140.egg-info/requires.txt
plonetheme.responsive1140.egg-info/top_level.txt
plonetheme/responsive1140/__init__.py
plonetheme/responsive1140/configure.zcml
plonetheme/responsive1140/rebuild_i18n.sh
plonetheme/responsive1140/tests.py
plonetheme/responsive1140/browser/__init__.py
plonetheme/responsive1140/browser/common.py
plonetheme/responsive1140/browser/configure.zcml
plonetheme/responsive1140/browser/interfaces.py
plonetheme/responsive1140/browser/sections.pt
plonetheme/responsive1140/locales/plonetheme.responsive1140.pot
plonetheme/responsive1140/locales/en/LC_MESSAGES/plonetheme.responsive1140.po
plonetheme/responsive1140/locales/fr/LC_MESSAGES/plonetheme.responsive1140.po
plonetheme/responsive1140/profiles/default/browserlayer.xml
plonetheme/responsive1140/profiles/default/cssregistry.xml
plonetheme/responsive1140/profiles/default/jsregistry.xml
plonetheme/responsive1140/profiles/default/metadata.xml
plonetheme/responsive1140/profiles/default/skins.xml
plonetheme/responsive1140/profiles/default/theme.xml
plonetheme/responsive1140/profiles/default/viewlets.xml
plonetheme/responsive1140/skins/plonetheme_responsive1140_custom/public.css
plonetheme/responsive1140/static/index.html
plonetheme/responsive1140/static/manifest.cfg
plonetheme/responsive1140/static/rules.xml
plonetheme/responsive1140/static/theme-one.html
plonetheme/responsive1140/static/theme-three.html
plonetheme/responsive1140/static/theme-two-left.html
plonetheme/responsive1140/static/theme-two-right.html
plonetheme/responsive1140/static/css/1140.css
plonetheme/responsive1140/static/css/ie.css
plonetheme/responsive1140/static/images/arrowDown.png
plonetheme/responsive1140/static/images/arrowRight.png
plonetheme/responsive1140/static/images/contenttypes-sprite.png
plonetheme/responsive1140/static/images/link_icon.png
plonetheme/responsive1140/static/images/pb_close.png
