Metadata-Version: 1.0
Name: plonetheme.responsive1140
Version: 1.1
Summary: A responsive theme for Plone
Home-page: https://github.com/collective/plonetheme.responsive1140
Author: JeanMichel FRANCOIS aka toutpt
Author-email: toutpt@gmail.com
License: GPL
Keywords: plone
Platform: UNKNOWN
Classifier: Programming Language :: Python
Classifier: Framework :: Plone
Classifier: Framework :: Plone :: 4.0
Classifier: Framework :: Plone :: 4.1
Classifier: Framework :: Plone :: 4.2
